pyNetSocket/__init__.py
pyNetSocket/docs/__init__.py
pyNetSocket/docs/callbacks.py
pyNetSocket/docs/client.py
pyNetSocket/docs/server.py
pyNetSocket-1.1.5.dist-info/LICENSE
pyNetSocket-1.1.5.dist-info/METADATA
pyNetSocket-1.1.5.dist-info/WHEEL
pyNetSocket-1.1.5.dist-info/top_level.txt
pyNetSocket-1.1.5.dist-info/RECORD
