Metadata-Version: 2.1
Name: pyNetSocket
Version: 1.1.5
Summary: A simple networking library for python
Home-page: https://github.com/DrSparky2k7/PyNetSocket
Author: AdityaIyer2k7
Author-email: adityaiyer2007@gmail.com
Keywords: networking,sockets,simple networking,simple sockets,pyNetSockets,pyNetSocket
Classifier: Programming Language :: Python :: 3
Classifier: License :: OSI Approved :: MIT License
Classifier: Operating System :: OS Independent
Requires-Python: >=3.6
License-File: LICENSE
